our_browser/__main__.py
our_browser/browser.py
our_browser/data/our_browser.ico
our_browser/data/smile_10.png
our_browser/draw_commons.py
our_browser/drawing.py
our_browser/examples/app_chat.py
our_browser/examples/app_listview.py
our_browser/examples/app_react.py
our_browser/examples/htmls/cancel.png
our_browser/examples/htmls/chat.html
our_browser/examples/htmls/div_big_height.html
our_browser/examples/htmls/div_flex.html
our_browser/examples/htmls/div_flex_vertical.html
our_browser/examples/htmls/div_image.html
our_browser/examples/htmls/div_long_text.html
our_browser/examples/htmls/div_procents.html
our_browser/examples/htmls/div_with_text.html
our_browser/examples/htmls/dropfile.png
our_browser/examples/htmls/search.png
our_browser/examples/htmls/send.png
our_browser/examples/htmls/settings.png
our_browser/examples/htmls/three_dots.png
our_browser/examples/htmls/tree.png
our_browser/examples/htmls/user_black.png
our_browser/ext_depends.py
our_browser/listview.py
our_browser/noder/example/listview.html
our_browser/noder/example/tst.html
our_browser/noder/noder.py
our_browser/noder/styler.py
our_browser/os_help.py
our_browser/react.py
our_browser/test/__init__.py
our_browser/test/test_simple.py
our_browser-0.1.1.dist-info/METADATA
our_browser-0.1.1.dist-info/WHEEL
our_browser-0.1.1.dist-info/RECORD
