Metadata-Version: 2.1
Name: our-browser
Version: 0.1.1
Summary: 
Author: wind
Author-email: andreev@compas.ru
Requires-Python: >=3.8,<4.0
Classifier: Programming Language :: Python :: 3
Classifier: Programming Language :: Python :: 3.8
Classifier: Programming Language :: Python :: 3.9
Classifier: Programming Language :: Python :: 3.10
Classifier: Programming Language :: Python :: 3.11
Requires-Dist: pycairo (>=1.24.0,<2.0.0)
Requires-Dist: wxPython (>=4.2.1,<5.0.0)
